aiorobinhood/__init__.py
aiorobinhood/client.py
aiorobinhood/decorators.py
aiorobinhood/exceptions.py
aiorobinhood/models.py
aiorobinhood/urls.py
aiorobinhood-2.1.0.dist-info/LICENSE
aiorobinhood-2.1.0.dist-info/METADATA
aiorobinhood-2.1.0.dist-info/WHEEL
aiorobinhood-2.1.0.dist-info/top_level.txt
aiorobinhood-2.1.0.dist-info/RECORD
