Metadata-Version: 2.1
Name: aiorobinhood
Version: 2.1.0
Summary: Asynchronous Robinhood HTTP client
Home-page: https://github.com/omikader/aiorobinhood
Author: Omar Abdelkader
Author-email: omikader@gmail.com
License: MIT
Keywords: robinhood,asyncio,python3,stocks
Platform: UNKNOWN
Classifier: Programming Language :: Python
Classifier: Programming Language :: Python :: 3
Classifier: Programming Language :: Python :: 3.7
Classifier: Programming Language :: Python :: 3.8
Requires-Python: >=3.7
Requires-Dist: aiohttp (<4.0,>=3.6)
Requires-Dist: yarl (<2.0,>=1.4)
Provides-Extra: dev
Requires-Dist: black ; extra == 'dev'
Requires-Dist: cryptography ; extra == 'dev'
Requires-Dist: flake8 ; extra == 'dev'
Requires-Dist: isort ; extra == 'dev'
Requires-Dist: mypy ; extra == 'dev'
Requires-Dist: pytest ; extra == 'dev'
Requires-Dist: pytest-aiohttp ; extra == 'dev'
Requires-Dist: pytest-asyncio ; extra == 'dev'
Requires-Dist: pytest-cov ; extra == 'dev'
Provides-Extra: docs
Requires-Dist: aiohttp-theme ; extra == 'docs'
Requires-Dist: sphinx ; extra == 'docs'
Requires-Dist: sphinx-autodoc-typehints ; extra == 'docs'
